sw_ops_common/__init__.py
sw_ops_common/asyncio/__init__.py
sw_ops_common/asyncio/db_util.py
sw_ops_common/asyncio/redis_util.py
sw_ops_common/config/__init__.py
sw_ops_common/config/load_config.py
sw_ops_common/db_util.py
sw_ops_common/log.py
sw_ops_common/redis_util.py
sw_ops_common-0.0.2.dist-info/WHEEL
sw_ops_common-0.0.2.dist-info/METADATA
sw_ops_common-0.0.2.dist-info/RECORD
