Metadata-Version: 2.1
Name: sw-ops-common
Version: 0.0.2
Summary: 
Author: xuxygo
Requires-Python: >=3.8,<4.0
Classifier: Programming Language :: Python :: 3
Classifier: Programming Language :: Python :: 3.10
Classifier: Programming Language :: Python :: 3.8
Classifier: Programming Language :: Python :: 3.9
Requires-Dist: DBUtils (==3.0.2)
Requires-Dist: PyMySQL (>=1.0.2,<2.0.0)
Requires-Dist: PyYAML (>=5.4.1,<6.0.0)
Requires-Dist: aiomysql
Requires-Dist: redis (>=4.2.2,<5.0.0)
